pydantic_core/__init__.py
pydantic_core/_pydantic_core.cpython-312.so
pydantic_core/core_schema.py
pydantic_core/py.typed
pydantic_core_qpython-2.24.4.1.dist-info/METADATA
pydantic_core_qpython-2.24.4.1.dist-info/WHEEL
pydantic_core_qpython-2.24.4.1.dist-info/top_level.txt
pydantic_core_qpython-2.24.4.1.dist-info/RECORD
