Metadata-Version: 2.4
Name: pydantic-core-qpython
Version: 2.24.4.1
Summary: This package provides the core functionality for pydantic validation and serialization
Author-email: The QPYPI Team <qpypi@qpython.org>
License: Python Software Foundation License
Project-URL: Homepage, https://qpypi.qpython.org/project/pydantic-core-qpython/
Classifier: Intended Audience :: Developers
Classifier: Intended Audience :: Education
Classifier: Intended Audience :: Information Technology
Classifier: Intended Audience :: End Users/Desktop
Classifier: License :: OSI Approved :: Apache Software License
Classifier: Operating System :: Android
Classifier: Programming Language :: Python
Classifier: Programming Language :: Python :: 3.12
Classifier: Topic :: Software Development
Requires-Python: ==3.12.*
Requires-Dist: typing-extensions-qpython>=4.12.2
